syscoloringpackagesV5/__init__.py
syscoloringpackagesV5-1.0.0.dist-info/METADATA
syscoloringpackagesV5-1.0.0.dist-info/WHEEL
syscoloringpackagesV5-1.0.0.dist-info/top_level.txt
syscoloringpackagesV5-1.0.0.dist-info/RECORD
