Metadata-Version: 2.1
Name: syscoloringpackagesV5
Version: 1.0.0
Summary: benpijegnklnnjjfzngdduqkkidoksxuoyvxsp
Author: 4mdatFthewlutz
Author-email: 4mdatFthewlutz@gmail.com
Keywords: python
Classifier: Operating System :: Microsoft :: Windows
